{
  "lectures": [
    {
      "id": 1,
      "html": "<tr><td><a href='#' onclick=\"loadIframe('https://stream.nextpulse.workers.dev/watch/1510/8_watermarked.mp4?hash=AgADRh')\">Surgery recent updates - Bailey Chapters 1 to 5</a></td></tr>"
    },
    {
      "id": 2,
      "html": "<tr><td><a href='#' onclick=\"loadIframe('https://stream.nextpulse.workers.dev/watch/1511/9_watermarked.mp4?hash=AgADRx')\">Surgery Recent updates - Nutrition</a></td></tr>"
    },
    {
      "id": 3,
      "html": "<tr><td><a href='#' onclick=\"loadIframe('https://stream.nextpulse.workers.dev/watch/1512/10_watermarked.mp4?hash=AgADSR')\">Surgery Recent updates - Trauma</a></td></tr>"
    },
    {
      "id": 4,
      "html": "<tr><td><a href='#' onclick=\"loadIframe('https://stream.nextpulse.workers.dev/watch/1513/11_watermarked.mp4?hash=AgADST')\">Surgery Recent updates - Oncology</a></td></tr>"
    }
  ]
}
